big_map_archive_api_client/__init__.py
big_map_archive_api_client/client/__init__.py
big_map_archive_api_client/client/api_client.py
big_map_archive_api_client/client/client_config.py
big_map_archive_api_client/client/rest_api_connection.py
big_map_archive_api_client/utils/__init__.py
big_map_archive_api_client/utils/requests.py
cli/__init__.py
cli/finales_db.py
cli/record.py
cli/root.py
finales_api_client/__init__.py
finales_api_client/client/__init__.py
finales_api_client/client/api_client.py
finales_api_client/client/client_config.py
finales_api_client/client/rest_api_connection.py
finales_api_client/client/test.py
finales_api_client/utils/__init__.py
big_map_archive_api_client-1.2.0.dist-info/METADATA
big_map_archive_api_client-1.2.0.dist-info/WHEEL
big_map_archive_api_client-1.2.0.dist-info/entry_points.txt
big_map_archive_api_client-1.2.0.dist-info/top_level.txt
big_map_archive_api_client-1.2.0.dist-info/RECORD
