Metadata-Version: 2.1
Name: big-map-archive-api-client
Version: 1.2.0
Summary: A CLI app to interact with BIG-MAP Archive data repositories
Home-page: https://github.com/materialscloud-org/big-map-archive-api-client
Author: BIG MAP Archive team
Author-email: big-map-archive@materialscloud.org
License: BIG-MAP Archive License
Platform: UNKNOWN
Requires-Dist: annotated-types (==0.5.0)
Requires-Dist: certifi (==2021.10.8)
Requires-Dist: charset-normalizer (==2.0.12)
Requires-Dist: click (==8.1.7)
Requires-Dist: docopt (==0.6.2)
Requires-Dist: idna (==3.3)
Requires-Dist: pipreqs (==0.4.11)
Requires-Dist: pydantic (==2.1.1)
Requires-Dist: pydantic-core (==2.4.0)
Requires-Dist: python-dotenv (==1.0.0)
Requires-Dist: PyYAML (==6.0.1)
Requires-Dist: requests (==2.27.1)
Requires-Dist: typing-extensions (==4.7.1)
Requires-Dist: urllib3 (==1.26.9)
Requires-Dist: yarg (==0.1.9)
